score/svg/__init__.py
score/svg/pyramid.py
score.svg-0.1.1.dist-info/DESCRIPTION.rst
score.svg-0.1.1.dist-info/METADATA
score.svg-0.1.1.dist-info/RECORD
score.svg-0.1.1.dist-info/WHEEL
score.svg-0.1.1.dist-info/metadata.json
score.svg-0.1.1.dist-info/top_level.txt
